pyarmor/cli/core/__init__.py
pyarmor/cli/core/features.py
pyarmor/cli/core/runtime.py
pyarmor_cli_core-7.6.5.dist-info/METADATA
pyarmor_cli_core-7.6.5.dist-info/WHEEL
pyarmor_cli_core-7.6.5.dist-info/top_level.txt
pyarmor_cli_core-7.6.5.dist-info/RECORD
